saffy/SignalManager.py
saffy/__init__.py
saffy/plugins/Filters.py
saffy/plugins/Fourier.py
saffy/plugins/Graphics.py
saffy/plugins/Hilbert.py
saffy/plugins/PluginManager.py
saffy/plugins/Welch.py
saffy/plugins/__init__.py
saffy/tests/PluginManager.py
saffy/tests/SignalManager.py
saffy/tests/__init__.py
saffy/tests/mocks/__init__.py
saffy/tests/mocks/sine_wave.py
saffy/tests/plugins/Fourier.py
saffy/tests/plugins/__init__.py
saffy-0.1.12.dist-info/METADATA
saffy-0.1.12.dist-info/RECORD
saffy-0.1.12.dist-info/WHEEL
saffy-0.1.12.dist-info/top_level.txt
