Metadata-Version: 2.1
Name: saffy
Version: 0.1.12
Summary: Signal Analysis Framework For You
Home-page: https://github.com/PPierzc/saffy
Author: Paweł A. Pierzchlewicz
Author-email: paul@teacode.io
License: MIT
Keywords: python,signal,analysis,EEG,neuroinformatics
Platform: UNKNOWN
Classifier: Development Status :: 3 - Alpha
Classifier: Intended Audience :: Developers
Classifier: Topic :: Software Development :: Build Tools
Classifier: License :: OSI Approved :: MIT License
Classifier: Programming Language :: Python :: 3
Requires-Dist: cycler (==0.10.0)
Requires-Dist: kiwisolver (==1.0.1)
Requires-Dist: matplotlib (==3.0.3)
Requires-Dist: mne (==0.17.1)
Requires-Dist: numpy (==1.16.2)
Requires-Dist: obci-readmanager (==1.1.3)
Requires-Dist: pandas (==0.24.2)
Requires-Dist: pyparsing (==2.3.1)
Requires-Dist: python-dateutil (==2.8.0)
Requires-Dist: pytz (==2018.9)
Requires-Dist: scipy (==1.2.1)
Requires-Dist: seaborn (==0.9.0)
Requires-Dist: six (==1.12.0)
